{
  "id": "ch-al0zO7cwXc3Iu8eibai9",
  "slug": "perler-bodenbelaege-orpund",
  "name": "Perler Bodenbeläge",
  "branchen": [
    "bodenleger"
  ],
  "adresse": {
    "strasse": "Hauptstrasse 202",
    "plz": "2552",
    "ort": "Orpund",
    "kanton": "Neuenburg",
    "land": "CH"
  },
  "kontakt": {
    "telefon": "+41765718338",
    "email": "info@perlerbodenbelaege.ch",
    "webseite": "https://perlerbodenbelaege.ch/index.php/contact"
  },
  "leistungen": [
    "Parkettverlegung",
    "Laminatverlegung",
    "Vinylbodenverlegung",
    "Teppichverlegung",
    "Unterbodenarbeiten",
    "Bodenrenovierung",
    "Epoxidbeschichtung",
    "Trittschalldämmung"
  ]
}