{
  "id": "ch-df3CtqxpOWNmnKTFUakS",
  "slug": "a-gantenbein-holzbau-ag-grabs",
  "name": "A. Gantenbein Holzbau AG",
  "branchen": [
    "dachdecker"
  ],
  "adresse": {
    "strasse": "Vorderdorfstrasse 12",
    "plz": "9472",
    "ort": "Grabs",
    "land": "CH"
  },
  "kontakt": {
    "telefon": "+41588811333",
    "email": "info@gantenbein-holzbau.ch",
    "webseite": "https://www.gantenbein-holzbau.ch"
  },
  "leistungen": [
    "Dachsanierung",
    "Neueindeckung",
    "Flachdachabdichtung",
    "Dachfenstereinbau",
    "Spenglerei",
    "Dachdämmung",
    "Photovoltaik-Montage",
    "Dachrinnenreinigung"
  ]
}