{
  "id": "ch-ML5wXWaYO2zpCXuAPkPf",
  "slug": "kropf-holz-gmbh-zuerich",
  "name": "Kropf Holz GmbH",
  "branchen": [
    "schreiner"
  ],
  "adresse": {
    "strasse": "Limmattalstrasse 142",
    "plz": "8049",
    "ort": "Zürich",
    "kanton": "Zürich",
    "land": "CH"
  },
  "kontakt": {
    "telefon": "+41443417212",
    "email": "info@kropf-holz.ch",
    "webseite": "https://kropf-holz.ch"
  },
  "leistungen": [
    "Massivholzmöbel",
    "Küchenbau",
    "Einbauschränke",
    "Fenster & Türen",
    "Innenausbau",
    "Treppenbau",
    "Badmöbel",
    "Holzreparatur"
  ]
}