{
  "id": "ch-odeiXIiEOziRsAQIzwjY",
  "slug": "albula-gartenbau-gmbh-30-jahre-scanfs",
  "name": "Albula Gartenbau GmbH – 30 Jahre",
  "branchen": [
    "gartenbau"
  ],
  "adresse": {
    "strasse": "Via Maistra 11",
    "plz": "7525",
    "ort": "Scanfs",
    "kanton": "Graubünden",
    "land": "CH"
  },
  "kontakt": {
    "telefon": "+41793535311",
    "email": "albula-gartenbau@bluewin.ch",
    "webseite": "https://www.albula-gartenbau.ch"
  },
  "leistungen": [
    "Gartengestaltung",
    "Rasenanlage",
    "Bewässerungssysteme",
    "Terrassengestaltung",
    "Bepflanzung & Baumschnitt",
    "Gartenunterhalt",
    "Naturstein & Pflasterung",
    "Schwimmteich & Biotop"
  ],
  "googlePlaceId": "ChIJFWdniHJkg0cRV_2T5GmCgHU",
  "google_fetched": true,
  "ratingCached": {
    "rating": 5,
    "user_ratings_total": 5,
    "reviews": [
      {
        "author_name": "Monika Buetler",
        "author_photo": "/images/reviews/albula-gartenbau-gmbh-30-jahre-scanfs/reviewer_1.jpg",
        "rating": 5,
        "text": "Professionell, kompetent, zuverlässig, schnell und freundlich. Wir sind äusserst zufrieden mit der Zusammenarbeit und können Albula Gartenbau wärmstens weiterempfehlen.\nPro-Tipp: Engadiner Hängenelken!",
        "time": 1777620768,
        "relative_time_description": "vor einem Monat"
      },
      {
        "author_name": "Helen Bürgler",
        "author_photo": "/images/reviews/albula-gartenbau-gmbh-30-jahre-scanfs/reviewer_2.jpg",
        "rating": 5,
        "text": "Wir sind begeistert von unserem neuen Sitzplatz. Danke an S. und M. Gutzweiler, die uns mit Ideen, Unterstützung und guter Ausführung dazu verholfen haben. H. und A. B.",
        "time": 1535617153,
        "relative_time_description": "vor 7 Jahren"
      },
      {
        "author_name": "Joshua Cruiser",
        "author_photo": "/images/reviews/albula-gartenbau-gmbh-30-jahre-scanfs/reviewer_3.jpg",
        "rating": 5,
        "text": "Habe eine Blume bekommen 10/10 würde ich weiterempfehlen",
        "time": 1620371730,
        "relative_time_description": "vor 5 Jahren"
      },
      {
        "author_name": "Manfred Gross",
        "author_photo": "/images/reviews/albula-gartenbau-gmbh-30-jahre-scanfs/reviewer_4.jpg",
        "rating": 5,
        "text": "Die Albula Gartenbau GmbH hat in unseren Garten eine ästhetisch schöne, handwerklich meisterlich gefertigte Trockenmauer errichtet, die unser Haus aufwertet und uns grosse Freude bereitet!",
        "time": 1781000380,
        "relative_time_description": "in der letzten Woche"
      },
      {
        "author_name": "cuci pinchera",
        "author_photo": "/images/reviews/albula-gartenbau-gmbh-30-jahre-scanfs/reviewer_5.jpg",
        "rating": 5,
        "text": "",
        "time": 1495814752,
        "relative_time_description": "vor 9 Jahren"
      }
    ],
    "last_updated": "2026-06-15"
  }
}
