{
  "id": "ch-rxWkAHykoB1XmUsUIIQ7",
  "slug": "maler-zug-farb-und-raumdesign-steffi-hohberg-zug",
  "name": "Maler Zug / Farb und Raumdesign Steffi Hohberg",
  "branchen": [
    "maler"
  ],
  "adresse": {
    "strasse": "Bernoldweg 9",
    "plz": "6300",
    "ort": "Zug",
    "kanton": "Zug",
    "land": "CH"
  },
  "kontakt": {
    "telefon": "+41795555625",
    "email": "steffi.hohberg@gmx.ch",
    "webseite": "https://www.farb-raumdesign-steffi-hohberg.ch"
  },
  "leistungen": [
    "Innenanstrich",
    "Aussenanstrich",
    "Fassadenrenovierung",
    "Tapezierarbeiten",
    "Dekorputz",
    "Holzschutzanstrich",
    "Farbberatung",
    "Grafittibeseitigung"
  ]
}