{
  "id": "ch-wBKTDhAAqgDkjspnSAw5",
  "slug": "loner-gmbh-mollis",
  "name": "Loner GmbH",
  "branchen": [
    "bodenleger"
  ],
  "adresse": {
    "strasse": "Feldbach 2",
    "plz": "8753",
    "ort": "Mollis",
    "kanton": "Glarus",
    "land": "CH"
  },
  "kontakt": {
    "telefon": "+41556124147",
    "email": "info@loner-gmbh.ch",
    "webseite": "https://www.loner-gmbh.ch"
  },
  "leistungen": [
    "Parkettverlegung",
    "Laminatverlegung",
    "Vinylbodenverlegung",
    "Teppichverlegung",
    "Unterbodenarbeiten",
    "Bodenrenovierung",
    "Epoxidbeschichtung",
    "Trittschalldämmung"
  ]
}