{
  "id": "ch-YCD5ZvtRxwtG5WpTEeW3",
  "slug": "generelli-idraulica-sa-locarno",
  "name": "GENERELLI IDRAULICA SA",
  "branchen": [
    "sanitaer"
  ],
  "adresse": {
    "strasse": "Via Domenico Galli 34",
    "plz": "6600",
    "ort": "Locarno",
    "kanton": "Tessin",
    "land": "CH"
  },
  "kontakt": {
    "telefon": "+41917515426",
    "email": "info@generelli-idraulica.ch",
    "webseite": "https://www.generelli-idraulica.ch"
  },
  "leistungen": [
    "Badezimmerinstallation",
    "Badezimmersanierung",
    "Sanitärinstallation",
    "Rohrreparatur",
    "Rohreinigung",
    "Wasseraufbereitung",
    "Leckortung",
    "Boileraustausch"
  ]
}