{
  "id": "ch-zVdLXDDnZ3PJ0XYjqDHN",
  "slug": "rca-vitrerie-veranda-antraygues-fabien-fully",
  "name": "RCA vitrerie & véranda Antraygues Fabien",
  "branchen": [
    "glaser"
  ],
  "adresse": {
    "strasse": "Chem. de l'Industrie 29A",
    "plz": "1926",
    "ort": "Fully",
    "kanton": "Wallis",
    "land": "CH"
  },
  "kontakt": {
    "telefon": "+41791931561",
    "email": "info@rca-vitrerie.ch",
    "webseite": "https://www.rca-vitrerie.ch"
  },
  "leistungen": [
    "Fensterverglasung",
    "Isolierverglasung",
    "Glastüren & Trennwände",
    "Wintergarten",
    "Duschkabinen",
    "Spiegel",
    "Sicherheitsglas",
    "Glaserservice & Notfallreparatur"
  ]
}