{
  "id": "ch-ZlX99OqB9soJJMGXVANy",
  "slug": "italkeramik-toffen",
  "name": "ITALKERAMIK",
  "branchen": [
    "fliesenleger"
  ],
  "adresse": {
    "strasse": "Bernstrasse 3",
    "plz": "3125",
    "ort": "Toffen",
    "kanton": "Bern",
    "land": "CH"
  },
  "kontakt": {
    "telefon": "+41319527878",
    "email": "info@italkeramik.ch",
    "webseite": "https://italkeramik.ch/home.html"
  },
  "leistungen": [
    "Badezimmergestaltung",
    "Bodenverlegung",
    "Wandverkleidung",
    "Terrassen & Aussenanlagen",
    "Naturstein & Mosaik",
    "Fugensanierung",
    "Duschbereich",
    "Küchenspiegel"
  ]
}